aioatomapi/__init__.py
aioatomapi/api_options_pb2.py
aioatomapi/api_pb2.py
aioatomapi/client.py
aioatomapi/connection.py
aioatomapi/core.py
aioatomapi/host_resolver.py
aioatomapi/log_reader.py
aioatomapi/model.py
aioatomapi/reconnect_logic.py
aioatomapi/util.py
aioatomapi-9.1.3.dist-info/LICENSE
aioatomapi-9.1.3.dist-info/METADATA
aioatomapi-9.1.3.dist-info/WHEEL
aioatomapi-9.1.3.dist-info/top_level.txt
aioatomapi-9.1.3.dist-info/RECORD
