Metadata-Version: 2.1
Name: aioatomapi
Version: 9.1.3
Summary: Python API for interacting with Atom devices.
Home-page: UNKNOWN
Author: Otto Winter
Author-email: atom@nabucasa.com
License: MIT
Download-URL: https://github.com/mssaleh/aioatomapi/archive/9.1.3.zip
Platform: UNKNOWN
Requires-Python: >=3.7
License-File: LICENSE
Requires-Dist: protobuf (<4.0,>=3.12.2)
Requires-Dist: zeroconf (<1.0,>=0.28.0)
Requires-Dist: noiseprotocol (<1.0,>=0.3.1)
